cellphonedb/__init__.py
cellphonedb/cellphonedb_cli.py
cellphonedb/src/__init__.py
cellphonedb/src/api_endpoints/__init__.py
cellphonedb/src/api_endpoints/terminal_api/__init__.py
cellphonedb/src/api_endpoints/terminal_api/method_terminal_api_endpoints/__init__.py
cellphonedb/src/api_endpoints/terminal_api/method_terminal_api_endpoints/method_terminal_commands.py
cellphonedb/src/api_endpoints/terminal_api/query_terminal_api_endpoints/__init__.py
cellphonedb/src/api_endpoints/terminal_api/query_terminal_api_endpoints/query_terminal_commands.py
cellphonedb/src/api_endpoints/web_api/__init__.py
cellphonedb/src/api_endpoints/web_api/routes.py
cellphonedb/src/api_endpoints/web_api/web_api_endpoint_base.py
cellphonedb/src/api_endpoints/web_api/query_web_api_endpoints/__init__.py
cellphonedb/src/api_endpoints/web_api/query_web_api_endpoints/query_web_api_routes.py
cellphonedb/src/api_endpoints/web_api/query_web_api_endpoints/web_endpoint_query_autocomplete.py
cellphonedb/src/api_endpoints/web_api/query_web_api_endpoints/web_endpoint_query_find_interactions_by_element.py
cellphonedb/src/api_endpoints/web_api/query_web_api_endpoints/complex/__init__.py
cellphonedb/src/api_endpoints/web_api/query_web_api_endpoints/complex/query_complex_web_api_routes.py
cellphonedb/src/api_endpoints/web_api/query_web_api_endpoints/complex/web_endpoint_query_complex_deconvoluted.py
cellphonedb/src/api_endpoints/web_api/query_web_api_endpoints/interaction/__init__.py
cellphonedb/src/api_endpoints/web_api/query_web_api_endpoints/interaction/query_interaction_web_api_routes.py
cellphonedb/src/api_endpoints/web_api/query_web_api_endpoints/interaction/web_endpoint_query_interaction_gene.py
cellphonedb/src/app/__init__.py
cellphonedb/src/app/app_config.py
cellphonedb/src/app/app_logger.py
cellphonedb/src/app/cellphonedb_app.py
cellphonedb/src/app/cpdb_app.py
cellphonedb/src/app/config/base_config.yml
cellphonedb/src/app/config/core.yml
cellphonedb/src/app/config/docker_test.yml
CellNet-1.1.1.3.dist-info/LICENSE
CellNet-1.1.1.3.dist-info/METADATA
CellNet-1.1.1.3.dist-info/WHEEL
CellNet-1.1.1.3.dist-info/entry_points.txt
CellNet-1.1.1.3.dist-info/top_level.txt
CellNet-1.1.1.3.dist-info/RECORD
