Metadata-Version: 2.1
Name: CellNet
Version: 1.1.1.3
Summary: UNKNOWN
Home-page: UNKNOWN
Author: Lee Hong Kai
Author-email: leehongkai@gmail.com
Maintainer: CJM Lab
License: MIT
Platform: UNKNOWN
Requires-Dist: click (<6.7.99,>=6.7)
Requires-Dist: numpy
Requires-Dist: pandas (<0.23.99,>=0.23)
Requires-Dist: flask (<1.0.99,>=1.0)
Requires-Dist: Flask-RESTful (<0.3.99,>=0.3)
Requires-Dist: Flask-Testing (<0.7.99,>=0.7)
Requires-Dist: SQLAlchemy (<1.2.99,>=1.2)
Requires-Dist: PyYAML (<3.13.99,>=3.13)
Requires-Dist: requests (<2.19.99,>=2.19)
